clifashion/__init__.py
clifashion/clifashion.py
clifashion-0.1.4.dist-info/LICENSE
clifashion-0.1.4.dist-info/METADATA
clifashion-0.1.4.dist-info/WHEEL
clifashion-0.1.4.dist-info/top_level.txt
clifashion-0.1.4.dist-info/RECORD
