Metadata-Version: 2.1
Name: clifashion
Version: 0.1.4
Summary: Awesome terminal input and output functions for Python 3.x scripts.
Home-page: UNKNOWN
Author: Luca Saladino
Author-email: sal65535@protonmail.com
License: UNKNOWN
Platform: UNKNOWN
Classifier: Programming Language :: Python :: 3
Classifier: License :: Freeware
Classifier: Operating System :: OS Independent
Requires-Python: >=3.9
License-File: LICENSE
